safirpy/__init__.py
safirpy/func.py
safirpy/func_dump.py
safirpy/gui.py
safirpy/gui2.py
safirpy/gui_fun.py
safirpy/tests.py
safirpy/ui_test.py
safirpy/mc/__init__.py
safirpy/mc/__main__.py
SafirPy-0.0.6.dist-info/LICENSE
SafirPy-0.0.6.dist-info/METADATA
SafirPy-0.0.6.dist-info/WHEEL
SafirPy-0.0.6.dist-info/top_level.txt
SafirPy-0.0.6.dist-info/RECORD
