Metadata-Version: 2.1
Name: SafirPy
Version: 0.0.6
Summary: A Safir wrapper for Monte Carlo simulations
Home-page: https://github.com/fsepy/safirpy
Author: Yan Fu
Author-email: fuyans@gmail.com
License: UNKNOWN
Download-URL: https://github.com/fsepy/safirpy/archive/master.zip
Keywords: fire safety,structural fire engineering,structural engineering,probabilistic,safir
Platform: UNKNOWN
Classifier: Programming Language :: Python :: 3
Classifier: Development Status :: 3 - Alpha
Classifier: Environment :: Other Environment
Classifier: Intended Audience :: Developers
Classifier: License :: OSI Approved :: MIT License
Classifier: Operating System :: OS Independent
Classifier: Topic :: Scientific/Engineering
Requires-Dist: numpy (>=1.15.2)
Requires-Dist: pandas (>=0.23.4)
Requires-Dist: scipy (>=1.1.0)
Requires-Dist: seaborn (>=0.9.0)
Requires-Dist: ruamel.yaml (>=0.15.74)
